__init__.py
quantc/__init__.py
quantc/base_strategy.py
quantc/config.py
quantc/constant.py
quantc/data_object.py
quantc/db_util.py
quantc/quote_gateway.py
quantc/trade_gateway.py
quantc/util.py
quantc-0.0.5.dist-info/METADATA
quantc-0.0.5.dist-info/WHEEL
quantc-0.0.5.dist-info/top_level.txt
quantc-0.0.5.dist-info/RECORD
