Metadata-Version: 2.1
Name: quantc
Version: 0.0.5
Requires-Dist: msgpack
Requires-Dist: pandas
Requires-Dist: numpy
Requires-Dist: TA-Lib
